{
  "annotations": {
    "list": []
  },
  "editable": false,
  "fiscalYearStartMonth": 0,
  "graphTooltip": 1,
  "id": null,
  "links": [
    {
      "asDropdown": true,
      "icon": "external link",
      "includeVars": false,
      "keepTime": true,
      "tags": [
        "tutordex"
      ],
      "title": "All TutorDex Dashboards",
      "type": "dashboards"
    }
  ],
  "panels": [
    {
      "datasource": {
        "type": "prometheus",
        "uid": "prometheus"
      },
      "fieldConfig": {
        "defaults": {
          "color": {
            "mode": "palette-classic"
          },
          "mappings": [],
          "thresholds": {
            "mode": "absolute",
            "steps": [
              {
                "color": "green",
                "value": null
              },
              {
                "color": "yellow",
                "value": 1800
              },
              {
                "color": "red",
                "value": 3600
              }
            ]
          },
          "unit": "s"
        },
        "overrides": []
      },
      "gridPos": {
        "h": 8,
        "w": 12,
        "x": 0,
        "y": 0
      },
      "id": 1,
      "options": {
        "displayMode": "gradient",
        "maxVizHeight": 300,
        "minVizHeight": 16,
        "minVizWidth": 8,
        "namePlacement": "auto",
        "orientation": "horizontal",
        "reduceOptions": {
          "values": false,
          "calcs": [
            "lastNotNull"
          ],
          "fields": ""
        },
        "showUnfilled": true,
        "sizing": "auto",
        "valueMode": "color"
      },
      "targets": [
        {
          "datasource": {
            "type": "prometheus",
            "uid": "prometheus"
          },
          "expr": "time() - collector_last_message_timestamp_seconds{channel=~\"$channel\"}",
          "legendFormat": "{{channel}}",
          "refId": "A"
        }
      ],
      "title": "Channel Staleness (time since last message)",
      "type": "bargauge",
      "description": "Green: <30min, Yellow: 30-60min, Red: >60min"
    },
    {
      "datasource": {
        "type": "prometheus",
        "uid": "prometheus"
      },
      "fieldConfig": {
        "defaults": {
          "color": {
            "mode": "palette-classic"
          },
          "mappings": [],
          "max": 1,
          "min": 0,
          "thresholds": {
            "mode": "absolute",
            "steps": [
              {
                "color": "#C4162A",
                "value": null
              },
              {
                "color": "#FADE2A",
                "value": 0.9
              },
              {
                "color": "#37872D",
                "value": 0.95
              }
            ]
          },
          "unit": "ops/s"
        },
        "overrides": []
      },
      "gridPos": {
        "h": 8,
        "w": 12,
        "x": 12,
        "y": 0
      },
      "id": 2,
      "options": {
        "displayMode": "gradient",
        "maxVizHeight": 300,
        "minVizHeight": 16,
        "minVizWidth": 8,
        "namePlacement": "auto",
        "orientation": "horizontal",
        "reduceOptions": {
          "values": false,
          "calcs": [
            "mean"
          ],
          "fields": ""
        },
        "showUnfilled": true,
        "sizing": "auto",
        "valueMode": "color"
      },
      "targets": [
        {
          "datasource": {
            "type": "prometheus",
            "uid": "prometheus"
          },
          "expr": "sum by (channel) (rate(worker_parse_success_total{channel=~\"$channel\"}[1h])) / (sum by (channel) (rate(worker_parse_success_total{channel=~\"$channel\"}[1h])) + sum by (channel) (rate(worker_parse_failure_total{channel=~\"$channel\"}[1h])))",
          "legendFormat": "{{channel}}",
          "refId": "A"
        }
      ],
      "title": "Parse Success Rate by Channel",
      "type": "bargauge",
      "description": "Green: >95%, Yellow: 85-95%, Red: <85%"
    },
    {
      "datasource": {
        "type": "prometheus",
        "uid": "prometheus"
      },
      "fieldConfig": {
        "defaults": {
          "color": {
            "mode": "palette-classic"
          },
          "custom": {
            "axisCenteredZero": false,
            "axisColorMode": "text",
            "axisLabel": "msgs/min",
            "axisPlacement": "auto",
            "barAlignment": 0,
            "drawStyle": "line",
            "fillOpacity": 10,
            "gradientMode": "none",
            "hideFrom": {
              "tooltip": false,
              "viz": false,
              "legend": false
            },
            "lineInterpolation": "linear",
            "lineWidth": 2,
            "pointSize": 5,
            "scaleDistribution": {
              "type": "linear"
            },
            "showPoints": "never",
            "spanNulls": true,
            "stacking": {
              "mode": "none",
              "group": "A"
            },
            "thresholdsStyle": {
              "mode": "off"
            }
          },
          "mappings": [],
          "thresholds": {
            "mode": "absolute",
            "steps": [
              {
                "color": "green",
                "value": null
              }
            ]
          },
          "unit": "cpm"
        },
        "overrides": []
      },
      "gridPos": {
        "h": 8,
        "w": 24,
        "x": 0,
        "y": 8
      },
      "id": 3,
      "options": {
        "legend": {
          "calcs": [
            "last",
            "mean",
            "max"
          ],
          "displayMode": "table",
          "placement": "bottom",
          "showLegend": true
        },
        "tooltip": {
          "mode": "multi",
          "sort": "desc"
        }
      },
      "targets": [
        {
          "datasource": {
            "type": "prometheus",
            "uid": "prometheus"
          },
          "expr": "sum by (channel) (rate(collector_messages_seen_total{channel=~\"$channel\"}[5m])) * 60",
          "legendFormat": "{{channel}}",
          "refId": "A"
        }
      ],
      "title": "Message Volume by Channel (msgs/min)",
      "type": "timeseries"
    },
    {
      "datasource": {
        "type": "prometheus",
        "uid": "prometheus"
      },
      "fieldConfig": {
        "defaults": {
          "color": {
            "mode": "palette-classic"
          },
          "mappings": [],
          "thresholds": {
            "mode": "absolute",
            "steps": [
              {
                "color": "red",
                "value": null
              },
              {
                "color": "yellow",
                "value": -0.2
              },
              {
                "color": "green",
                "value": -0.05
              },
              {
                "color": "green",
                "value": 0.05
              },
              {
                "color": "yellow",
                "value": 0.5
              },
              {
                "color": "red",
                "value": 1
              }
            ]
          },
          "unit": "percentunit"
        },
        "overrides": []
      },
      "gridPos": {
        "h": 8,
        "w": 12,
        "x": 0,
        "y": 16
      },
      "id": 4,
      "options": {
        "displayMode": "gradient",
        "maxVizHeight": 300,
        "minVizHeight": 16,
        "minVizWidth": 8,
        "namePlacement": "auto",
        "orientation": "horizontal",
        "reduceOptions": {
          "values": false,
          "calcs": [
            "lastNotNull"
          ],
          "fields": ""
        },
        "showUnfilled": true,
        "sizing": "auto",
        "valueMode": "color"
      },
      "targets": [
        {
          "datasource": {
            "type": "prometheus",
            "uid": "prometheus"
          },
          "expr": "(sum by (channel) (rate(collector_messages_seen_total{channel=~\"$channel\"}[24h])) - sum by (channel) (rate(collector_messages_seen_total{channel=~\"$channel\"}[24h] offset $compare_period))) / sum by (channel) (rate(collector_messages_seen_total{channel=~\"$channel\"}[24h] offset $compare_period))",
          "legendFormat": "{{channel}}",
          "refId": "A"
        }
      ],
      "title": "Week-over-Week Volume Change",
      "type": "bargauge",
      "description": "Shows % change in message volume compared to last week. Red: >50% decline or >100% spike"
    },
    {
      "datasource": {
        "type": "prometheus",
        "uid": "prometheus"
      },
      "fieldConfig": {
        "defaults": {
          "color": {
            "mode": "palette-classic"
          },
          "custom": {
            "axisCenteredZero": false,
            "axisColorMode": "text",
            "axisLabel": "errors/min",
            "axisPlacement": "auto",
            "barAlignment": 0,
            "drawStyle": "line",
            "fillOpacity": 10,
            "gradientMode": "none",
            "hideFrom": {
              "tooltip": false,
              "viz": false,
              "legend": false
            },
            "lineInterpolation": "linear",
            "lineWidth": 2,
            "pointSize": 5,
            "scaleDistribution": {
              "type": "linear"
            },
            "showPoints": "never",
            "spanNulls": true,
            "stacking": {
              "mode": "none",
              "group": "A"
            },
            "thresholdsStyle": {
              "mode": "off"
            }
          },
          "mappings": [],
          "thresholds": {
            "mode": "absolute",
            "steps": [
              {
                "color": "#37872D",
                "value": null
              },
              {
                "color": "#FADE2A",
                "value": 0.01
              },
              {
                "color": "#C4162A",
                "value": 0.05
              }
            ]
          },
          "unit": "cpm"
        },
        "overrides": []
      },
      "gridPos": {
        "h": 8,
        "w": 12,
        "x": 12,
        "y": 16
      },
      "id": 5,
      "options": {
        "legend": {
          "calcs": [
            "last",
            "mean",
            "max"
          ],
          "displayMode": "table",
          "placement": "bottom",
          "showLegend": true
        },
        "tooltip": {
          "mode": "multi",
          "sort": "desc"
        }
      },
      "targets": [
        {
          "datasource": {
            "type": "prometheus",
            "uid": "prometheus"
          },
          "expr": "sum by (channel) (rate(worker_parse_failure_total{channel=~\"$channel\"}[5m])) * 60",
          "legendFormat": "{{channel}}",
          "refId": "A"
        }
      ],
      "title": "Parse Failures by Channel",
      "type": "timeseries",
      "description": "Error rate monitoring. High values require investigation."
    },
    {
      "datasource": {
        "type": "prometheus",
        "uid": "prometheus"
      },
      "fieldConfig": {
        "defaults": {
          "color": {
            "mode": "palette-classic"
          },
          "mappings": [],
          "max": 100,
          "min": 0,
          "thresholds": {
            "mode": "absolute",
            "steps": [
              {
                "color": "#C4162A",
                "value": null
              },
              {
                "color": "#FADE2A",
                "value": 0.9
              },
              {
                "color": "#37872D",
                "value": 0.95
              }
            ]
          },
          "unit": "percent"
        },
        "overrides": []
      },
      "gridPos": {
        "h": 8,
        "w": 12,
        "x": 0,
        "y": 24
      },
      "id": 6,
      "options": {
        "displayMode": "gradient",
        "maxVizHeight": 300,
        "minVizHeight": 16,
        "minVizWidth": 8,
        "namePlacement": "auto",
        "orientation": "horizontal",
        "reduceOptions": {
          "values": false,
          "calcs": [
            "lastNotNull"
          ],
          "fields": ""
        },
        "showUnfilled": true,
        "sizing": "auto",
        "valueMode": "color"
      },
      "targets": [
        {
          "datasource": {
            "type": "prometheus",
            "uid": "prometheus"
          },
          "expr": "(sum by (channel) (rate(worker_parse_success_total{channel=~\"$channel\"}[1h])) / (sum by (channel) (rate(worker_parse_success_total{channel=~\"$channel\"}[1h])) + sum by (channel) (rate(worker_parse_failure_total{channel=~\"$channel\"}[1h])))) * 100",
          "legendFormat": "{{channel}}",
          "refId": "A"
        }
      ],
      "title": "Channel Health Score (Parse Success %)",
      "type": "bargauge",
      "description": "Composite health score based on parse success rate. Green: >85%, Yellow: 70-85%, Red: <70%"
    },
    {
      "datasource": {
        "type": "prometheus",
        "uid": "prometheus"
      },
      "fieldConfig": {
        "defaults": {
          "color": {
            "mode": "palette-classic"
          },
          "custom": {
            "hideFrom": {
              "tooltip": false,
              "viz": false,
              "legend": false
            }
          },
          "mappings": [],
          "thresholds": {
            "mode": "absolute",
            "steps": []
          }
        },
        "overrides": []
      },
      "gridPos": {
        "h": 8,
        "w": 12,
        "x": 12,
        "y": 24
      },
      "id": 7,
      "options": {
        "displayLabels": [
          "percent",
          "name"
        ],
        "legend": {
          "displayMode": "table",
          "placement": "right",
          "showLegend": true,
          "values": [
            "value"
          ]
        },
        "pieType": "donut",
        "reduceOptions": {
          "values": false,
          "calcs": [
            "sum"
          ],
          "fields": ""
        },
        "tooltip": {
          "mode": "single",
          "sort": "none"
        }
      },
      "targets": [
        {
          "datasource": {
            "type": "prometheus",
            "uid": "prometheus"
          },
          "expr": "sum by (channel) (increase(collector_messages_seen_total{channel=~\"$channel\"}[$__range]))",
          "legendFormat": "{{channel}}",
          "refId": "A"
        }
      ],
      "title": "Message Distribution by Channel",
      "type": "piechart"
    }
  ],
  "refresh": "1m",
  "schemaVersion": 41,
  "style": "dark",
  "tags": [
    "tutordex",
    "channels",
    "health",
    "monitoring"
  ],
  "templating": {
    "list": [
      {
        "current": {
          "selected": true,
          "text": "All",
          "value": "$__all"
        },
        "datasource": {
          "type": "prometheus",
          "uid": "prometheus"
        },
        "definition": "label_values(collector_messages_seen_total, channel)",
        "hide": 0,
        "includeAll": true,
        "label": "Channel",
        "multi": true,
        "name": "channel",
        "options": [],
        "query": {
          "query": "label_values(collector_messages_seen_total, channel)",
          "refId": "PrometheusVariableQueryEditor-VariableQuery"
        },
        "refresh": 1,
        "regex": "",
        "skipUrlSync": false,
        "sort": 1,
        "type": "query"
      },
      {
        "current": {
          "selected": true,
          "text": "1 week",
          "value": "1w"
        },
        "hide": 0,
        "includeAll": false,
        "label": "Compare To",
        "multi": false,
        "name": "compare_period",
        "options": [
          {
            "selected": false,
            "text": "1 day",
            "value": "1d"
          },
          {
            "selected": true,
            "text": "1 week",
            "value": "1w"
          },
          {
            "selected": false,
            "text": "1 month",
            "value": "4w"
          }
        ],
        "query": "1d,1w,4w",
        "queryValue": "",
        "skipUrlSync": false,
        "type": "custom"
      }
    ]
  },
  "time": {
    "from": "now-24h",
    "to": "now"
  },
  "timepicker": {},
  "timezone": "browser",
  "title": "TutorDex Channel Health",
  "uid": "tutordex-channel-health",
  "version": 1
}
